README.md
setup.cfg
setup.py
cassiopeia_championgg/__init__.py
cassiopeia_championgg/core.py
cassiopeia_championgg/data.py
cassiopeia_championgg/datastores.py
cassiopeia_championgg/dto.py
cassiopeia_championgg/form_urls.py
cassiopeia_championgg/transformers.py
cassiopeia_championgg.egg-info/PKG-INFO
cassiopeia_championgg.egg-info/SOURCES.txt
cassiopeia_championgg.egg-info/dependency_links.txt
cassiopeia_championgg.egg-info/top_level.txt
cassiopeia_championgg.egg-info/zip-safe