Metadata-Version: 1.1
Name: cassiopeia-championgg
Version: 1.0.7
Summary: A plugin for the LoL wrapper Cassiopeia to use the champion.gg API.
Home-page: https://github.com/meraki-analytics/cassiopeia-plugins/tree/master/cassiopeia-championgg
Author: Jason Maldonis; Rob Rua
Author-email: team@merakianalytics.com
License: MIT
Platform: UNKNOWN
Classifier: Development Status :: 4 - Beta
Classifier: Programming Language :: Python :: 3
Classifier: Environment :: Web Environment
Classifier: Operating System :: OS Independent
Classifier: Intended Audience :: Developers
Classifier: License :: OSI Approved :: MIT License
Classifier: Topic :: Games/Entertainment
Classifier: Topic :: Games/Entertainment :: Real Time Strategy
Classifier: Topic :: Games/Entertainment :: Role-Playing
Classifier: Topic :: Software Development :: Libraries :: Python Modules
